{
  "project_info": {
    "project_number": "982096425868",
    "firebase_url": "https://environment-setup-db165.firebaseio.com",
    "project_id": "environment-setup-db165",
    "storage_bucket": "environment-setup-db165.appspot.com"
  },
  "client": [
    {
      "client_info": {
        "mobilesdk_app_id": "1:982096425868:android:7411c8887265f42bcf1ca9",
        "android_client_info": {
          "package_name": "com.example.my_environment_setup"
        }
      },
      "oauth_client": [
        {
          "client_id": "982096425868-h4fflujn3pp7s78e5ip005e2bq2tbqu4.apps.googleusercontent.com",
          "client_type": 3
        }
      ],
      "api_key": [
        {
          "current_key": "AIzaSyAmAQUD-9QL9KIdM65pBwoFQOQvA5U351M"
        }
      ],
      "services": {
        "appinvite_service": {
          "other_platform_oauth_client": [
            {
              "client_id": "982096425868-h4fflujn3pp7s78e5ip005e2bq2tbqu4.apps.googleusercontent.com",
              "client_type": 3
            }
          ]
        }
      }
    },
    {
      "client_info": {
        "mobilesdk_app_id": "1:982096425868:android:bf39ee8ecec963becf1ca9",
        "android_client_info": {
          "package_name": "com.example.relearn_iteration_one"
        }
      },
      "oauth_client": [
        {
          "client_id": "982096425868-h4fflujn3pp7s78e5ip005e2bq2tbqu4.apps.googleusercontent.com",
          "client_type": 3
        }
      ],
      "api_key": [
        {
          "current_key": "AIzaSyAmAQUD-9QL9KIdM65pBwoFQOQvA5U351M"
        }
      ],
      "services": {
        "appinvite_service": {
          "other_platform_oauth_client": [
            {
              "client_id": "982096425868-h4fflujn3pp7s78e5ip005e2bq2tbqu4.apps.googleusercontent.com",
              "client_type": 3
            }
          ]
        }
      }
    }
  ],
  "configuration_version": "1"
}